{
  "blocks": [
    {
      "type": "header",
      "text": {
        "type": "plain_text",
        "text": "Accessibility Report",
        "emoji": true
      }
    },
    {
      "type": "section",
      "text": {
        "type": "mrkdwn",
        "text": ":large_yellow_circle: *Status: Warning*\nTier: `full` | Pass Rate: *91%*"
      }
    },
    {
      "type": "divider"
    },
    {
      "type": "section",
      "fields": [
        {
          "type": "mrkdwn",
          "text": "*URLs Analyzed*\n67"
        },
        {
          "type": "mrkdwn",
          "text": "*Passing*\n:large_green_circle: 61"
        },
        {
          "type": "mrkdwn",
          "text": "*Warning*\n:large_yellow_circle: 6"
        },
        {
          "type": "mrkdwn",
          "text": "*Failing*\n:red_circle: 0"
        }
      ]
    },
    {
      "type": "divider"
    },
    {
      "type": "section",
      "text": {
        "type": "mrkdwn",
        "text": "*Worst Performing URLs (Sitemap)*"
      }
    },
    {
      "type": "section",
      "text": {
        "type": "mrkdwn",
        "text": ":warning: */agb*\nScore: 83% | Issues: 6\n  - `matIconAccessibility`: mat-icon used as interactive without accessible label. Screen readers cannot ann\n  - `matIconAccessibility`: mat-icon used as interactive without accessible label. Screen readers cannot ann\n  - `matIconAccessibility`: mat-icon used as interactive without accessible label. Screen readers cannot ann"
      }
    },
    {
      "type": "section",
      "text": {
        "type": "mrkdwn",
        "text": ":warning: */datenschutz*\nScore: 83% | Issues: 6\n  - `matIconAccessibility`: mat-icon used as interactive without accessible label. Screen readers cannot ann\n  - `matIconAccessibility`: mat-icon used as interactive without accessible label. Screen readers cannot ann\n  - `matIconAccessibility`: mat-icon used as interactive without accessible label. Screen readers cannot ann"
      }
    },
    {
      "type": "section",
      "text": {
        "type": "mrkdwn",
        "text": ":warning: */impressum*\nScore: 83% | Issues: 6\n  - `matIconAccessibility`: mat-icon used as interactive without accessible label. Screen readers cannot ann\n  - `matIconAccessibility`: mat-icon used as interactive without accessible label. Screen readers cannot ann\n  - `matIconAccessibility`: mat-icon used as interactive without accessible label. Screen readers cannot ann"
      }
    },
    {
      "type": "section",
      "text": {
        "type": "mrkdwn",
        "text": ":warning: */cookies*\nScore: 83% | Issues: 6\n  - `matIconAccessibility`: mat-icon used as interactive without accessible label. Screen readers cannot ann\n  - `matIconAccessibility`: mat-icon used as interactive without accessible label. Screen readers cannot ann\n  - `matIconAccessibility`: mat-icon used as interactive without accessible label. Screen readers cannot ann"
      }
    },
    {
      "type": "section",
      "text": {
        "type": "mrkdwn",
        "text": ":warning: */widerrufsrecht*\nScore: 83% | Issues: 6\n  - `matIconAccessibility`: mat-icon used as interactive without accessible label. Screen readers cannot ann\n  - `matIconAccessibility`: mat-icon used as interactive without accessible label. Screen readers cannot ann\n  - `matIconAccessibility`: mat-icon used as interactive without accessible label. Screen readers cannot ann"
      }
    },
    {
      "type": "divider"
    },
    {
      "type": "section",
      "text": {
        "type": "mrkdwn",
        "text": "*Internal Routes* (not in sitemap)\n76 routes | :large_green_circle: 9 | :large_yellow_circle: 40 | :red_circle: 1"
      }
    },
    {
      "type": "section",
      "text": {
        "type": "mrkdwn",
        "text": ":x: */verwaltung/fotoalbum*\nScore: 42% | Issues: 38\n  - `buttonNames`: Button missing accessible name. Screen readers cannot announce the button purpos\n  - `buttonNames`: Button missing accessible name. Screen readers cannot announce the button purpos\n  - `buttonNames`: Button missing accessible name. Screen readers cannot announce the button purpos"
      }
    },
    {
      "type": "section",
      "text": {
        "type": "mrkdwn",
        "text": ":warning: */konfigurator/reihenfolge*\nScore: 60% | Issues: 49\n  - `buttonNames`: Button missing accessible name. Screen readers cannot announce the button purpos\n  - `clickWithoutKeyboard`: Click handler without keyboard support. Keyboard users cannot activate this elem\n  - `clickWithoutRole`: Clickable element missing role. Screen readers cannot identify the element as in"
      }
    },
    {
      "type": "section",
      "text": {
        "type": "mrkdwn",
        "text": ":warning: */verwaltung/einladungen*\nScore: 61% | Issues: 12\n  - `clickWithoutKeyboard`: Click handler without keyboard support. Keyboard users cannot activate this elem\n  - `clickWithoutRole`: Clickable element missing role. Screen readers cannot identify the element as in\n  - `matIconAccessibility`: mat-icon used as interactive without accessible label. Screen readers cannot ann"
      }
    },
    {
      "type": "divider"
    },
    {
      "type": "context",
      "elements": [
        {
          "type": "mrkdwn",
          "text": "Generated by *mat-a11y* | 2025-12-12T21:05:58.803Z"
        }
      ]
    }
  ],
  "text": "Accessibility Report: Warning - 61/67 URLs passing (91%)"
}